optv/__init__.py
optv/calibration.c
optv/calibration.cp311-win_amd64.pyd
optv/calibration.pxd
optv/correspondences.c
optv/correspondences.cp311-win_amd64.pyd
optv/correspondences.pxd
optv/epipolar.c
optv/epipolar.cp311-win_amd64.pyd
optv/epipolar.pxd
optv/image_processing.c
optv/image_processing.cp311-win_amd64.pyd
optv/image_processing.pxd
optv/imgcoord.c
optv/imgcoord.cp311-win_amd64.pyd
optv/imgcoord.pxd
optv/orientation.c
optv/orientation.cp311-win_amd64.pyd
optv/orientation.pxd
optv/parameters.c
optv/parameters.cp311-win_amd64.pyd
optv/parameters.pxd
optv/segmentation.c
optv/segmentation.cp311-win_amd64.pyd
optv/segmentation.pxd
optv/tracker.c
optv/tracker.cp311-win_amd64.pyd
optv/tracker.pxd
optv/tracking_framebuf.c
optv/tracking_framebuf.cp311-win_amd64.pyd
optv/tracking_framebuf.pxd
optv/transforms.c
optv/transforms.cp311-win_amd64.pyd
optv/transforms.pxd
optv/vec_utils.pxd
optv/version.py
optv-0.3.1.dist-info/METADATA
optv-0.3.1.dist-info/WHEEL
optv-0.3.1.dist-info/top_level.txt
optv-0.3.1.dist-info/RECORD
