Metadata-Version: 2.4
Name: optv
Version: 0.3.1
Summary: OpenPTV Python bindings
Author-email: OpenPTV Community <openptv@googlegroups.com>
License: LGPL-3.0-or-later
Requires-Python: >=3.10
Requires-Dist: numpy==1.26.4
Requires-Dist: pyyaml
